__init__.py
account.py
app_service.py
bbt.py
ep.py
service_node.py
user.py
bumblebee_sdk_test-1.0.3.dist-info/LICENSE
bumblebee_sdk_test-1.0.3.dist-info/METADATA
bumblebee_sdk_test-1.0.3.dist-info/WHEEL
bumblebee_sdk_test-1.0.3.dist-info/top_level.txt
bumblebee_sdk_test-1.0.3.dist-info/RECORD
