Metadata-Version: 2.1
Name: bumblebee-sdk-test
Version: 1.0.3
Summary: Access the Bumblebee Networks Controller API and define account, endpoint node, service node, app service, endpoint, and user classes.
Classifier: License :: OSI Approved :: MIT License
Classifier: Programming Language :: Python
Classifier: Programming Language :: Python :: 3
License-File: LICENSE
Requires-Dist: attrs >=22.2.0
Requires-Dist: certifi >=2022.12.7
Requires-Dist: charset-normalizer >=3.1.0
Requires-Dist: click >=8.1.3
Requires-Dist: idna >=3.4
Requires-Dist: iniconfig >=2.0.0
Requires-Dist: MarkupSafe >=2.1.2
Requires-Dist: packaging >=23.0
Requires-Dist: pluggy >=1.0.0
Requires-Dist: pytest >=7.2.2
Requires-Dist: requests >=2.28.2
Requires-Dist: urllib3 >=1.26.15
Requires-Dist: Werkzeug >=2.2.3
